main.py
mii_cli-0.1.0.dist-info/licenses/LICENSE
mii_cli-0.1.0.dist-info/METADATA
mii_cli-0.1.0.dist-info/WHEEL
mii_cli-0.1.0.dist-info/entry_points.txt
mii_cli-0.1.0.dist-info/top_level.txt
mii_cli-0.1.0.dist-info/RECORD
