Metadata-Version: 2.4
Name: mii-cli
Version: 0.1.0
Summary: CLI tool for extracting and analyzing Mii files from Nintendo console database dumps
Requires-Python: >=3.13
License-File: LICENSE
Requires-Dist: typer>=0.17.4
Dynamic: license-file
